groups_sync/__init__.py
groups_sync/__settings.py
groups_sync/apps.py
groups_sync/settings.py
groups_sync/utils.py
groups_sync/management/__init__.py
groups_sync/management/commands/__init__.py
groups_sync/management/commands/export_groups_permissions.py
groups_sync/management/commands/sync_groups_permissions.py
django_groups_sync-0.0.4.dist-info/LICENSE
django_groups_sync-0.0.4.dist-info/METADATA
django_groups_sync-0.0.4.dist-info/WHEEL
django_groups_sync-0.0.4.dist-info/top_level.txt
django_groups_sync-0.0.4.dist-info/RECORD
