Metadata-Version: 2.1
Name: django-groups-sync
Version: 0.0.4
Summary: A set of management commands to export and sync Django User Groups permissions between environments.
Home-page: https://github.com/hansek/django-groups-sync
Author: Jan Tezner
Author-email: jan.tezner@gmail.com
License: License :: OSI Approved :: MIT License
Platform: UNKNOWN
Classifier: Intended Audience :: Developers
Classifier: Operating System :: OS Independent
Classifier: License :: OSI Approved :: MIT License
Classifier: Programming Language :: Python
Classifier: Programming Language :: Python :: 3
Classifier: Intended Audience :: Developers
